certbot_dns_he_simple.py
certbot_dns_he_simple-1.0.0.dist-info/licenses/LICENSE
certbot_dns_he_simple-1.0.0.dist-info/METADATA
certbot_dns_he_simple-1.0.0.dist-info/WHEEL
certbot_dns_he_simple-1.0.0.dist-info/entry_points.txt
certbot_dns_he_simple-1.0.0.dist-info/top_level.txt
certbot_dns_he_simple-1.0.0.dist-info/RECORD
