Metadata-Version: 2.4
Name: certbot-dns-he-simple
Version: 1.0.0
Summary: Simple Hurricane Electric DNS Authenticator plugin for Certbot
Author-email: Tobias Girstmair <tobi@isticktoit.net>
License-Expression: BSD-2-Clause
Project-URL: Homepage, https://git.gir.st/certbot-dns-he-simple.git
License-File: LICENSE
Requires-Dist: certbot
Requires-Dist: zope.interface
Requires-Dist: requests
Dynamic: license-file
